docs/README.md
hledger_fifo/__init__.py
hledger_fifo/__main__.py
hledger_fifo/avg.py
hledger_fifo/avg_info.py
hledger_fifo/checks.py
hledger_fifo/cli.py
hledger_fifo/fifo.py
hledger_fifo/fifo_info.py
hledger_fifo/files.py
hledger_fifo/hl.py
hledger_fifo/info.py
hledger_fifo/lib.py
tests/__init__.py
tests/lots_data.py
tests/test__main__.py
tests/test_avg.py
tests/test_checks.py
tests/test_fifo.py
tests/test_files.py
tests/test_hl.py
tests/test_info.py
tests/test_lib.py
venv/bin/rst2html.py
venv/bin/rst2html4.py
venv/bin/rst2html5.py
venv/bin/rst2latex.py
venv/bin/rst2man.py
venv/bin/rst2odt.py
venv/bin/rst2odt_prepstyles.py
venv/bin/rst2pseudoxml.py
venv/bin/rst2s5.py
venv/bin/rst2xetex.py
venv/bin/rst2xml.py
venv/bin/rstpep2html.py
hledger_fifo-0.1.0.dist-info/METADATA
hledger_fifo-0.1.0.dist-info/WHEEL
hledger_fifo-0.1.0.dist-info/entry_points.txt
hledger_fifo-0.1.0.dist-info/top_level.txt
hledger_fifo-0.1.0.dist-info/RECORD
