Metadata-Version: 2.1
Name: hledger-fifo
Version: 0.1.0
License: MIT License
Project-URL: homepage, https://github.com/edkedk99/hledger-fifo
Project-URL: documentation, https://edkedk99.github.io/hledger-fifo/
Project-URL: repository, https://github.com/edkedk99/hledger-fifo
Requires-Python: >=3.8
Requires-Dist: click
Requires-Dist: rich-click
Requires-Dist: tabulate
Requires-Dist: pyxirr
